flimtools.py
linleastsquares.py
napariflim.py
flimtools-0.0.4.dist-info/LICENSE
flimtools-0.0.4.dist-info/METADATA
flimtools-0.0.4.dist-info/WHEEL
flimtools-0.0.4.dist-info/top_level.txt
flimtools-0.0.4.dist-info/RECORD
