Metadata-Version: 2.1
Name: flimtools
Version: 0.0.4
Summary: A set of tools to do linear unmixing and phasor analysis on FLIM data.
Home-page: https://github.com/jayunruh/FLIM_tools
Author: Jay Unruh
License: GNU GPLv2
Requires-Python: >=3.6
License-File: LICENSE
Requires-Dist: numpy
Requires-Dist: numba
Requires-Dist: matplotlib
Requires-Dist: napari
Requires-Dist: magicgui
